__init__.py
units.py
simple_unit_system-0.0.8.dist-info/LICENSE
simple_unit_system-0.0.8.dist-info/METADATA
simple_unit_system-0.0.8.dist-info/WHEEL
simple_unit_system-0.0.8.dist-info/top_level.txt
simple_unit_system-0.0.8.dist-info/RECORD
