Metadata-Version: 2.1
Name: simple-unit-system
Version: 0.0.8
Summary: A framework for applying physical units and performing unit conversions, for scientific and engineering analyses, based on NIST conversions and constants
Project-URL: Bug Reports, https://github.com/jeffcodez/PhysicalUnits/issues
Project-URL: Source, https://github.com/jeffcodez/PhysicalUnits
Keywords: unit,units,physical,system,SI,NIST,engineering,scientific,measurements,weights,physics
Requires-Python: >=3, <4
License-File: LICENSE
